pp_out/__init__.py
pp_out/command_line.py
pp_out/printff.py
pp_out-1.5.dist-info/METADATA
pp_out-1.5.dist-info/WHEEL
pp_out-1.5.dist-info/entry_points.txt
pp_out-1.5.dist-info/top_level.txt
pp_out-1.5.dist-info/RECORD
