Metadata-Version: 2.1
Name: pp-out
Version: 1.5
Summary: 视频运维平台适用于不同规模的视频监控系统的日常运维管理
Home-page: UNKNOWN
Author: Chang Hao
Author-email: mixpplus@gmail.com
License: UNKNOWN
Keywords: demo,out,test
Platform: UNKNOWN
